BioNet/__init__.py
BioNet/bionet.py
BioNet/logging_config.py
BioNet/models.py
BioNet/plugin_interface.py
BioNet/plugin_manager.py
BioNet-0.1.1.dist-info/METADATA
BioNet-0.1.1.dist-info/WHEEL
BioNet-0.1.1.dist-info/top_level.txt
BioNet-0.1.1.dist-info/RECORD
